chat_agent/__init__.py
chat_agent/cli.py
chat_agent/config.py
chat_agent/main.py
chat_agent/storage.py
zchat-0.1.9.dist-info/METADATA
zchat-0.1.9.dist-info/WHEEL
zchat-0.1.9.dist-info/entry_points.txt
zchat-0.1.9.dist-info/top_level.txt
zchat-0.1.9.dist-info/RECORD
